SIPO/SIPO.vhdl
library ieee;
use ieee.std_logic_1164.all;
use ieee.numeric_std.all;

entity sipo is
	port
	(
		serial_in   :  in std_logic;
		clk         :  in std_logic;
		lat         :  in std_logic;
		parallel_out:  out std_logic_vector(7 downto 0)
	);
end sipo;

architecture behave of sipo is
--BEGIN DECLARATIONS
	signal buffer_out : std_logic_vector(7 downto 0) := "00000000";
--END DECLARATIONS

--BEGIN BEHAVE
begin 
	-- CLOCKING PROCESS
	risingClock : process(clk)
		begin
			if rising_edge(clk) then
				--Add new bit every rising clock
				buffer_out <= buffer_out(6 downto 0) & serial_in;
			end if;
	end process;

	-- LATCHING PROCESS
	risingLatch : process(lat)
		begin
			if rising_edge(lat) then
				--Add new bit every rising clock
				parallel_out <= buffer_out;
			end if;
	end process;
end behave;
--END BEHAVE

SIPO/SIPO_TB.vhdl
library ieee;
use ieee.std_logic_1164.all;

entity sipo_tb is
end sipo_tb;

--Definition of Internal Architecture 
architecture test of sipo_tb is
--BEGIN DECLARATIONS
	component sipo
		port
		(
			serial_in   :  in std_logic;
			clk         :  in std_logic;
			lat         :  in std_logic;
			parallel_out:  out std_logic_vector(7 downto 0)
		);
	end component;

	signal SERIAL_IN, CLK, LAT : std_logic := '0';
	signal PARALLEL_OUT : std_logic_vector(7 downto 0);
--END DECLARATIONS

begin
	uut : sipo port map (serial_in => SERIAL_IN, clk => CLK, lat => LAT, parallel_out => PARALLEL_OUT);

	process begin

		wait for 1 ns;
		for index in 0 to 7 loop
			CLK <= '1';
			wait for 1 ns;
			SERIAL_IN <= SERIAL_IN xor '1';
			CLK <= '0';
			wait for 1 ns;
		end loop;
		
		LAT <= '1';
		wait for 1 ns;

		assert false report "Test finished" severity note;
		wait;

	end process;

end test;

SIPO/sipo.vcd
$date
  Sun Mar 28 17:39:22 2021
$end
$version
  GHDL v0
$end
$timescale
  1 fs
$end
$scope module standard $end
$upscope $end
$scope module std_logic_1164 $end
$upscope $end
$scope module numeric_std $end
$upscope $end
$scope module sipo_tb $end
$var reg 1 ! serial_in $end
$var reg 1 " clk $end
$var reg 1 # lat $end
$var reg 8 $ parallel_out[7:0] $end
$scope module uut $end
$var reg 1 % serial_in $end
$var reg 1 & clk $end
$var reg 1 ' lat $end
$var reg 8 ( parallel_out[7:0] $end
$var reg 8 ) buffer_out[7:0] $end
$upscope $end
$upscope $end
$enddefinitions $end
#0
0!
0"
0#
bUUUUUUUU $
0%
0&
0'
bUUUUUUUU (
b00000000 )
#1000000
1"
1&
#2000000
1!
0"
1%
0&
#3000000
1"
1&
b00000001 )
#4000000
0!
0"
0%
0&
#5000000
1"
1&
b00000010 )
#6000000
1!
0"
1%
0&
#7000000
1"
1&
b00000101 )
#8000000
0!
0"
0%
0&
#9000000
1"
1&
b00001010 )
#10000000
1!
0"
1%
0&
#11000000
1"
1&
b00010101 )
#12000000
0!
0"
0%
0&
#13000000
1"
1&
b00101010 )
#14000000
1!
0"
1%
0&
#15000000
1"
1&
b01010101 )
#16000000
0!
0"
0%
0&
#17000000
1#
b01010101 $
1'
b01010101 (
