PISO/PISO.vhdl
library ieee;
use ieee.std_logic_1164.all;
use ieee.numeric_std.all;

entity piso is
	port
	(
		parallel_in :  in std_logic_vector(7 downto 0);
		clk         :  in std_logic;
		lat         :  in std_logic;
		serial_out  :  out std_logic
	);
end piso;

architecture behave of piso is
	--BEGIN DECLARATIONS
		signal buffer_in : std_logic_vector(7 downto 0) := "00000000";
		signal cnt : integer range 0 to 7 := 0;
	--END DECLARATIONS

	--BEGIN BEHAVE
	begin 
		-- CLOCKING PROCESS
		risingClock : process(clk)
			begin
				if rising_edge(clk) then
					--push new bit every rising clock, lsb first
					serial_out <= buffer_in(cnt);

					-- increment shifting counter
					if cnt = 7 then 
						cnt <= 0;
					else cnt <= cnt + 1;
					end if;

				end if;
		end process;

		-- LATCHING PROCESS
		risingLatch : process(lat)
			begin
				if rising_edge(lat) then
					--Add new bit every rising clock
					buffer_in <= parallel_in;
				end if;
		end process;
end behave;
--END BEHAVE

PISO/PISO_TB.vhdl
library ieee;
use ieee.std_logic_1164.all;

entity piso_tb is
end piso_tb;

--Definition of Internal Architecture 
architecture test of piso_tb is
--BEGIN DECLARATIONS
	component piso
		port
		(
			parallel_in :  in std_logic_vector(7 downto 0);
			clk         :  in std_logic;
			lat         :  in std_logic;
			serial_out  :  out std_logic
		);
	end component;

	signal SERIAL_OUT, CLK, LAT : std_logic := '0';
	signal PARALLEL_IN : std_logic_vector(7 downto 0) := "11110000";
--END DECLARATIONS

begin
	uut : piso port map (serial_out => SERIAL_OUT, clk => CLK, lat => LAT, parallel_in => PARALLEL_IN);

	process begin

		LAT <= '1';
		wait for 1 ns;
		LAT <= '0';

		for index in 0 to 30 loop
			CLK <= CLK xor '1';
			

			if index = 15 then
				LAT <= '1';
				wait for 1 ns;
				LAT <= '0';
			else
				wait for 1 ns;
			
			end if ;
			
		end loop;
		
		assert false report "Test finished" severity note;
		wait;

	end process;

end test;

PISO/piso.vcd
$date
  Sun Mar 28 17:42:48 2021
$end
$version
  GHDL v0
$end
$timescale
  1 fs
$end
$scope module standard $end
$upscope $end
$scope module std_logic_1164 $end
$upscope $end
$scope module numeric_std $end
$upscope $end
$scope module piso_tb $end
$var reg 1 ! serial_out $end
$var reg 1 " clk $end
$var reg 1 # lat $end
$var reg 8 $ parallel_in[7:0] $end
$scope module uut $end
$var reg 8 % parallel_in[7:0] $end
$var reg 1 & clk $end
$var reg 1 ' lat $end
$var reg 1 ( serial_out $end
$var reg 8 ) buffer_in[7:0] $end
$var integer 32 * cnt $end
$upscope $end
$upscope $end
$enddefinitions $end
#0
U!
0"
1#
b11110000 $
b11110000 %
0&
1'
U(
b11110000 )
b0 *
#1000000
0!
1"
0#
1&
0'
0(
b1 *
#2000000
0"
0&
#3000000
1"
1&
b10 *
#4000000
0"
0&
#5000000
1"
1&
b11 *
#6000000
0"
0&
#7000000
1"
1&
b100 *
#8000000
0"
0&
#9000000
1!
1"
1&
1(
b101 *
#10000000
0"
0&
#11000000
1"
1&
b110 *
#12000000
0"
0&
#13000000
1"
1&
b111 *
#14000000
0"
0&
#15000000
1"
1&
b0 *
#16000000
0"
1#
0&
1'
#17000000
0!
1"
0#
1&
0'
0(
b1 *
#18000000
0"
0&
#19000000
1"
1&
b10 *
#20000000
0"
0&
#21000000
1"
1&
b11 *
#22000000
0"
0&
#23000000
1"
1&
b100 *
#24000000
0"
0&
#25000000
1!
1"
1&
1(
b101 *
#26000000
0"
0&
#27000000
1"
1&
b110 *
#28000000
0"
0&
#29000000
1"
1&
b111 *
#30000000
0"
0&
#31000000
1"
1&
b0 *
