FULL_ADDER/FULL_ADDER.vhdl
library ieee;

use ieee.std_logic_1164.all;

entity full_adder is
	port
	(
		a:  in std_ulogic;
		b:  in std_ulogic;
		cin: in std_ulogic;
		q: out std_ulogic;
		cout: out std_ulogic
	);
end full_adder;

architecture behave of full_adder is
begin
	q <= a xor b xor cin;
	cout <= (a and b) or (a and cin) or (b and cin);
end behave;

FULL_ADDER/FULL_ADDER_TB.vhdl
library ieee;
use ieee.std_logic_1164.all;

entity full_adder_tb is
end full_adder_tb;

--Definition of Internal Architecture 
architecture test of full_adder_tb is
	component full_adder
		port
		(
			a:  in std_ulogic;
			b:  in std_ulogic;
			cin: in std_ulogic;
			q: out std_ulogic;
			cout: out std_ulogic
		);
	end component;

	signal A, B, CIN, Q, COUT : std_ulogic;

begin
	uut : full_adder port map (a => A, b => B, cin => CIN, q => Q, cout => COUT);

	process begin

		CIN <= 'X'; 
		B  <= 'X'; 
		A  <= 'X'; 
		wait for 1 ns;
		CIN <= '0'; 
		B  <= '0'; 
		A  <= '0'; 
		wait for 1 ns;
		CIN <= '0'; 
		B  <= '0'; 
		A  <= '1'; 
		wait for 1 ns;
		CIN <= '0'; 
		B  <= '1'; 
		A  <= '0'; 
		wait for 1 ns;
		CIN <= '0'; 
		B  <= '1'; 
		A  <= '1'; 
		wait for 1 ns;
		CIN <= '1'; 
		B  <= '0'; 
		A  <= '0'; 
		wait for 1 ns;
		CIN <= '1'; 
		B  <= '0'; 
		A  <= '1'; 
		wait for 1 ns;
		CIN <= '1'; 
		B  <= '1'; 
		A  <= '0'; 
		wait for 1 ns;
		CIN <= '1'; 
		B  <= '1'; 
		A  <= '1'; 
		wait for 1 ns;

		assert false report "Test finished" severity note;
		wait;

	end process;

end test;

FULL_ADDER/full_adder.vcd
$date
  Sun Mar 28 17:32:55 2021
$end
$version
  GHDL v0
$end
$timescale
  1 fs
$end
$scope module standard $end
$upscope $end
$scope module std_logic_1164 $end
$upscope $end
$scope module full_adder_tb $end
$var reg 1 ! a $end
$var reg 1 " b $end
$var reg 1 # cin $end
$var reg 1 $ q $end
$var reg 1 % cout $end
$scope module uut $end
$var reg 1 & a $end
$var reg 1 ' b $end
$var reg 1 ( cin $end
$var reg 1 ) q $end
$var reg 1 * cout $end
$upscope $end
$upscope $end
$enddefinitions $end
#0
X!
X"
X#
X$
X%
X&
X'
X(
X)
X*
#1000000
0!
0"
0#
0$
0%
0&
0'
0(
0)
0*
#2000000
1!
1$
1&
1)
#3000000
0!
1"
0&
1'
#4000000
1!
0$
1%
1&
0)
1*
#5000000
0!
0"
1#
1$
0%
0&
0'
1(
1)
0*
#6000000
1!
0$
1%
1&
0)
1*
#7000000
0!
1"
0&
1'
#8000000
1!
1$
1&
1)
